pyguievent.py
pyguievent-0.0.9.post0.dist-info/METADATA
pyguievent-0.0.9.post0.dist-info/WHEEL
pyguievent-0.0.9.post0.dist-info/licenses/LICENSE
pyguievent-0.0.9.post0.dist-info/RECORD
