Metadata-Version: 2.4
Name: pyguievent
Version: 0.0.9.post0
Summary: A simple tool to create events to PySimpleGUI or PySimpleGUI4
Project-URL: Homepage, https://github.com/yunluo/pyguievent
Project-URL: Repository, https://github.com/yunluo/pyguievent
Author-email: yunluo <sp91@qq.com>
License: GPL-3.0
License-File: LICENSE
Keywords: FreeSimpleGUI,GUI,PySimpleEvent,PySimpleGUI,PySimpleGUI4,events for simplegui,pyguievent
Requires-Python: >=3
